[{"MediaSourceInfo":{"Chapters":[],"Protocol":"File","Type":"Default","Container":"mkv","Size":20566234309,"Name":"精灵旅社2 (2015) - 1080p.Remux.H.264.DTS-HD MA 5.1-404","IsRemote":true,"HasMixedProtocols":false,"RunTimeTicks":53583680000,"SupportsTranscoding":true,"SupportsDirectStream":true,"SupportsDirectPlay":true,"IsInfiniteStream":false,"RequiresOpening":false,"RequiresClosing":false,"RequiresLooping":false,"SupportsProbing":true,"MediaStreams":[{"Codec":"h264","Language":"eng","TimeBase":"1/1000","Title":"精灵旅社2","VideoRange":"SDR","DisplayTitle":"1080p H264","DisplayLanguage":"English","NalLengthSize":"4","IsInterlaced":false,"BitRate":30705221,"BitDepth":8,"RefFrames":1,"IsDefault":true,"IsForced":false,"IsHearingImpaired":false,"Height":1080,"Width":1920,"AverageFrameRate":23.976025,"RealFrameRate":23.976025,"Profile":"High","Type":"Video","AspectRatio":"16:9","Index":0,"IsExternal":false,"IsTextSubtitleStream":false,"SupportsExternalStream":false,"Protocol":"File","PixelFormat":"yuv420p","Level":41,"IsAnamorphic":false,"ExtendedVideoType":"None","ExtendedVideoSubType":"None","ExtendedVideoSubTypeDescription":"None","AttachmentSize":0},{"Codec":"dts","Language":"eng","TimeBase":"1/1000","Title":"英语","DisplayTitle":"English DTS-HD MA 5.1 (默认)","DisplayLanguage":"English","IsInterlaced":false,"ChannelLayout":"5.1","BitDepth":16,"Channels":6,"SampleRate":48000,"IsDefault":true,"IsForced":false,"IsHearingImpaired":false,"Profile":"DTS-HD MA","Type":"Audio","Index":1,"IsExternal":false,"IsTextSubtitleStream":false,"SupportsExternalStream":false,"Protocol":"File","ExtendedVideoType":"None","ExtendedVideoSubType":"None","ExtendedVideoSubTypeDescription":"None","AttachmentSize":0},{"Codec":"dts","Language":"chi","TimeBase":"1/1000","Title":"国语[次世代公映国语]","DisplayTitle":"Chinese DTS-HD MA 5.1","DisplayLanguage":"Chinese","IsInterlaced":false,"ChannelLayout":"5.1","BitDepth":16,"Channels":6,"SampleRate":48000,"IsDefault":false,"IsForced":false,"IsHearingImpaired":false,"Profile":"DTS-HD MA","Type":"Audio","Index":2,"IsExternal":false,"IsTextSubtitleStream":false,"SupportsExternalStream":false,"Protocol":"File","ExtendedVideoType":"None","ExtendedVideoSubType":"None","ExtendedVideoSubTypeDescription":"None","AttachmentSize":0},{"Codec":"ac3","Language":"chi","TimeBase":"1/1000","Title":"国语[台湾]","DisplayTitle":"Chinese AC3 5.1","DisplayLanguage":"Chinese","IsInterlaced":false,"ChannelLayout":"5.1","BitRate":640000,"Channels":6,"SampleRate":48000,"IsDefault":false,"IsForced":false,"IsHearingImpaired":false,"Type":"Audio","Index":3,"IsExternal":false,"IsTextSubtitleStream":false,"SupportsExternalStream":false,"Protocol":"File","ExtendedVideoType":"None","ExtendedVideoSubType":"None","ExtendedVideoSubTypeDescription":"None","AttachmentSize":0},{"Codec":"ac3","Language":"chi","TimeBase":"1/1000","Title":"国语[粤语]","DisplayTitle":"Chinese AC3 5.1","DisplayLanguage":"Chinese","IsInterlaced":false,"ChannelLayout":"5.1","BitRate":640000,"Channels":6,"SampleRate":48000,"IsDefault":false,"IsForced":false,"IsHearingImpaired":false,"Type":"Audio","Index":4,"IsExternal":false,"IsTextSubtitleStream":false,"SupportsExternalStream":false,"Protocol":"File","ExtendedVideoType":"None","ExtendedVideoSubType":"None","ExtendedVideoSubTypeDescription":"None","AttachmentSize":0},{"Codec":"PGSSUB","Language":"chi","TimeBase":"1/1000","Title":"简英双语特效字幕[英语]","DisplayTitle":"Chinese (默认 PGSSUB)","DisplayLanguage":"Chinese","IsInterlaced":false,"IsDefault":true,"IsForced":false,"IsHearingImpaired":false,"Type":"Subtitle","Index":5,"IsExternal":false,"IsTextSubtitleStream":false,"SupportsExternalStream":false,"Protocol":"File","ExtendedVideoType":"None","ExtendedVideoSubType":"None","ExtendedVideoSubTypeDescription":"None","AttachmentSize":0,"SubtitleLocationType":"InternalStream"},{"Codec":"PGSSUB","Language":"chi","TimeBase":"1/1000","Title":"简英双语字幕[英语]","DisplayTitle":"Chinese (PGSSUB)","DisplayLanguage":"Chinese","IsInterlaced":false,"IsDefault":false,"IsForced":false,"IsHearingImpaired":false,"Height":1080,"Width":1920,"Type":"Subtitle","Index":6,"IsExternal":false,"IsTextSubtitleStream":false,"SupportsExternalStream":false,"Protocol":"File","ExtendedVideoType":"None","ExtendedVideoSubType":"None","ExtendedVideoSubTypeDescription":"None","AttachmentSize":0,"SubtitleLocationType":"InternalStream"},{"Codec":"PGSSUB","Language":"chi","TimeBase":"1/1000","Title":"繁英双语字幕[英语]","DisplayTitle":"Chinese (PGSSUB)","DisplayLanguage":"Chinese","IsInterlaced":false,"IsDefault":false,"IsForced":false,"IsHearingImpaired":false,"Height":1080,"Width":1920,"Type":"Subtitle","Index":7,"IsExternal":false,"IsTextSubtitleStream":false,"SupportsExternalStream":false,"Protocol":"File","ExtendedVideoType":"None","ExtendedVideoSubType":"None","ExtendedVideoSubTypeDescription":"None","AttachmentSize":0,"SubtitleLocationType":"InternalStream"},{"Codec":"PGSSUB","Language":"chi","TimeBase":"1/1000","Title":"简体字幕[英语]","DisplayTitle":"Chinese Simplified (PGSSUB)","DisplayLanguage":"Chinese Simplified","IsInterlaced":false,"IsDefault":false,"IsForced":false,"IsHearingImpaired":false,"Height":1080,"Width":1920,"Type":"Subtitle","Index":8,"IsExternal":false,"IsTextSubtitleStream":false,"SupportsExternalStream":false,"Protocol":"File","ExtendedVideoType":"None","ExtendedVideoSubType":"None","ExtendedVideoSubTypeDescription":"None","AttachmentSize":0,"SubtitleLocationType":"InternalStream"},{"Codec":"PGSSUB","Language":"chi","TimeBase":"1/1000","Title":"繁体字幕[英语]","DisplayTitle":"Chinese Traditional (PGSSUB)","DisplayLanguage":"Chinese Traditional","IsInterlaced":false,"IsDefault":false,"IsForced":false,"IsHearingImpaired":false,"Height":1080,"Width":1920,"Type":"Subtitle","Index":9,"IsExternal":false,"IsTextSubtitleStream":false,"SupportsExternalStream":false,"Protocol":"File","ExtendedVideoType":"None","ExtendedVideoSubType":"None","ExtendedVideoSubTypeDescription":"None","AttachmentSize":0,"SubtitleLocationType":"InternalStream"},{"Codec":"PGSSUB","Language":"chi","TimeBase":"1/1000","Title":"简体字幕[次世代公映国语]","DisplayTitle":"Chinese Simplified (PGSSUB)","DisplayLanguage":"Chinese Simplified","IsInterlaced":false,"IsDefault":false,"IsForced":false,"IsHearingImpaired":false,"Height":1080,"Width":1920,"Type":"Subtitle","Index":10,"IsExternal":false,"IsTextSubtitleStream":false,"SupportsExternalStream":false,"Protocol":"File","ExtendedVideoType":"None","ExtendedVideoSubType":"None","ExtendedVideoSubTypeDescription":"None","AttachmentSize":0,"SubtitleLocationType":"InternalStream"},{"Codec":"PGSSUB","Language":"chi","TimeBase":"1/1000","Title":"繁体字幕[次世代公映国语]","DisplayTitle":"Chinese Traditional (PGSSUB)","DisplayLanguage":"Chinese Traditional","IsInterlaced":false,"IsDefault":false,"IsForced":false,"IsHearingImpaired":false,"Height":1080,"Width":1920,"Type":"Subtitle","Index":11,"IsExternal":false,"IsTextSubtitleStream":false,"SupportsExternalStream":false,"Protocol":"File","ExtendedVideoType":"None","ExtendedVideoSubType":"None","ExtendedVideoSubTypeDescription":"None","AttachmentSize":0,"SubtitleLocationType":"InternalStream"}],"Formats":[],"Bitrate":30705221,"RequiredHttpHeaders":{},"AddApiKeyToDirectStreamUrl":false,"ReadAtNativeFramerate":false},"Chapters":[{"StartPositionTicks":0,"Name":"第 01 章","MarkerType":"Chapter","ChapterIndex":0},{"StartPositionTicks":3464710000,"Name":"第 02 章","MarkerType":"Chapter","ChapterIndex":1},{"StartPositionTicks":5576390000,"Name":"第 03 章","MarkerType":"Chapter","ChapterIndex":2},{"StartPositionTicks":7897050000,"Name":"第 04 章","MarkerType":"Chapter","ChapterIndex":3},{"StartPositionTicks":11691250000,"Name":"第 05 章","MarkerType":"Chapter","ChapterIndex":4},{"StartPositionTicks":13625680000,"Name":"第 06 章","MarkerType":"Chapter","ChapterIndex":5},{"StartPositionTicks":18053030000,"Name":"第 07 章","MarkerType":"Chapter","ChapterIndex":6},{"StartPositionTicks":21727110000,"Name":"第 08 章","MarkerType":"Chapter","ChapterIndex":7},{"StartPositionTicks":24009810000,"Name":"第 09 章","MarkerType":"Chapter","ChapterIndex":8},{"StartPositionTicks":27543760000,"Name":"第 10 章","MarkerType":"Chapter","ChapterIndex":9},{"StartPositionTicks":30824540000,"Name":"第 11 章","MarkerType":"Chapter","ChapterIndex":10},{"StartPositionTicks":34149110000,"Name":"第 12 章","MarkerType":"Chapter","ChapterIndex":11},{"StartPositionTicks":38419200000,"Name":"第 13 章","MarkerType":"Chapter","ChapterIndex":12},{"StartPositionTicks":41128170000,"Name":"第 14 章","MarkerType":"Chapter","ChapterIndex":13},{"StartPositionTicks":44094040000,"Name":"第 15 章","MarkerType":"Chapter","ChapterIndex":14},{"StartPositionTicks":47158770000,"Name":"第 16 章","MarkerType":"Chapter","ChapterIndex":15}]}]