[{"MediaSourceInfo":{"Protocol":"File","Id":"8194ca5cbfaeecf377f76d88af5eba0c","Path":"/strm/123_movie/剧情片/美丽心灵 (2001) {tmdb-453}/美丽心灵 (2001) - 1080p.BluRay.H.265-FRDS.strm","Type":"Default","Container":"mkv","Size":5760130816,"Name":"美丽心灵 (2001) - 1080p.BluRay.H.265-FRDS","IsRemote":true,"HasMixedProtocols":false,"RunTimeTicks":81191530000,"SupportsTranscoding":true,"SupportsDirectStream":true,"SupportsDirectPlay":true,"IsInfiniteStream":false,"RequiresOpening":false,"RequiresClosing":false,"RequiresLooping":false,"SupportsProbing":false,"MediaStreams":[{"Codec":"hevc","ColorPrimaries":"bt709","TimeBase":"1/1000","VideoRange":"SDR","DisplayTitle":"1080p HEVC","IsInterlaced":false,"BitRate":5675597,"BitDepth":10,"RefFrames":1,"IsDefault":true,"IsForced":false,"IsHearingImpaired":false,"Height":1040,"Width":1920,"AverageFrameRate":23.976025,"RealFrameRate":23.976025,"Profile":"Main 10","Type":"Video","AspectRatio":"24:13","Index":0,"IsExternal":false,"IsTextSubtitleStream":false,"SupportsExternalStream":false,"Protocol":"File","PixelFormat":"yuv420p10le","Level":120,"IsAnamorphic":false,"ExtendedVideoType":"None","ExtendedVideoSubType":"None","ExtendedVideoSubTypeDescription":"None","AttachmentSize":0},{"Codec":"ac3","Language":"eng","TimeBase":"1/1000","DisplayTitle":"English AC3 5.1 (默认)","DisplayLanguage":"English","IsInterlaced":false,"ChannelLayout":"5.1","BitRate":640000,"Channels":6,"SampleRate":48000,"IsDefault":true,"IsForced":false,"IsHearingImpaired":false,"Type":"Audio","Index":1,"IsExternal":false,"IsTextSubtitleStream":false,"SupportsExternalStream":false,"Protocol":"File","ExtendedVideoType":"None","ExtendedVideoSubType":"None","ExtendedVideoSubTypeDescription":"None","AttachmentSize":0},{"Codec":"ac3","Language":"chi","TimeBase":"1/1000","DisplayTitle":"Chinese Simplified AC3 5.1","DisplayLanguage":"Chinese Simplified","IsInterlaced":false,"ChannelLayout":"5.1","BitRate":448000,"Channels":6,"SampleRate":48000,"IsDefault":false,"IsForced":false,"IsHearingImpaired":false,"Type":"Audio","Index":2,"IsExternal":false,"IsTextSubtitleStream":false,"SupportsExternalStream":false,"Protocol":"File","ExtendedVideoType":"None","ExtendedVideoSubType":"None","ExtendedVideoSubTypeDescription":"None","AttachmentSize":0},{"Codec":"PGSSUB","Language":"eng","TimeBase":"1/1000","DisplayTitle":"English (默认 PGSSUB)","DisplayLanguage":"English","IsInterlaced":false,"IsDefault":true,"IsForced":false,"IsHearingImpaired":false,"Type":"Subtitle","Index":3,"IsExternal":false,"IsTextSubtitleStream":false,"SupportsExternalStream":false,"Protocol":"File","ExtendedVideoType":"None","ExtendedVideoSubType":"None","ExtendedVideoSubTypeDescription":"None","AttachmentSize":0,"SubtitleLocationType":"InternalStream"},{"Codec":"PGSSUB","Language":"chi","TimeBase":"1/1000","DisplayTitle":"Chinese Simplified (PGSSUB)","DisplayLanguage":"Chinese Simplified","IsInterlaced":false,"IsDefault":false,"IsForced":false,"IsHearingImpaired":false,"Type":"Subtitle","Index":4,"IsExternal":false,"IsTextSubtitleStream":false,"SupportsExternalStream":false,"Protocol":"File","ExtendedVideoType":"None","ExtendedVideoSubType":"None","ExtendedVideoSubTypeDescription":"None","AttachmentSize":0,"SubtitleLocationType":"InternalStream"},{"Codec":"PGSSUB","Language":"chi","TimeBase":"1/1000","DisplayTitle":"Chinese Simplified (PGSSUB)","DisplayLanguage":"Chinese Simplified","IsInterlaced":false,"IsDefault":false,"IsForced":false,"IsHearingImpaired":false,"Type":"Subtitle","Index":5,"IsExternal":false,"IsTextSubtitleStream":false,"SupportsExternalStream":false,"Protocol":"File","ExtendedVideoType":"None","ExtendedVideoSubType":"None","ExtendedVideoSubTypeDescription":"None","AttachmentSize":0,"SubtitleLocationType":"InternalStream"},{"Codec":"PGSSUB","Language":"chi","TimeBase":"1/1000","DisplayTitle":"Chinese Simplified (PGSSUB)","DisplayLanguage":"Chinese Simplified","IsInterlaced":false,"IsDefault":false,"IsForced":false,"IsHearingImpaired":false,"Type":"Subtitle","Index":6,"IsExternal":false,"IsTextSubtitleStream":false,"SupportsExternalStream":false,"Protocol":"File","ExtendedVideoType":"None","ExtendedVideoSubType":"None","ExtendedVideoSubTypeDescription":"None","AttachmentSize":0,"SubtitleLocationType":"InternalStream"},{"Codec":"PGSSUB","Language":"chi","TimeBase":"1/1000","DisplayTitle":"Chinese Simplified (PGSSUB)","DisplayLanguage":"Chinese Simplified","IsInterlaced":false,"IsDefault":false,"IsForced":false,"IsHearingImpaired":false,"Type":"Subtitle","Index":7,"IsExternal":false,"IsTextSubtitleStream":false,"SupportsExternalStream":false,"Protocol":"File","ExtendedVideoType":"None","ExtendedVideoSubType":"None","ExtendedVideoSubTypeDescription":"None","AttachmentSize":0,"SubtitleLocationType":"InternalStream"},{"Codec":"PGSSUB","Language":"chi","TimeBase":"1/1000","DisplayTitle":"Chinese Simplified (PGSSUB)","DisplayLanguage":"Chinese Simplified","IsInterlaced":false,"IsDefault":false,"IsForced":false,"IsHearingImpaired":false,"Type":"Subtitle","Index":8,"IsExternal":false,"IsTextSubtitleStream":false,"SupportsExternalStream":false,"Protocol":"File","ExtendedVideoType":"None","ExtendedVideoSubType":"None","ExtendedVideoSubTypeDescription":"None","AttachmentSize":0,"SubtitleLocationType":"InternalStream"},{"Codec":"PGSSUB","Language":"chi","TimeBase":"1/1000","DisplayTitle":"Chinese Simplified (PGSSUB)","DisplayLanguage":"Chinese Simplified","IsInterlaced":false,"IsDefault":false,"IsForced":false,"IsHearingImpaired":false,"Type":"Subtitle","Index":9,"IsExternal":false,"IsTextSubtitleStream":false,"SupportsExternalStream":false,"Protocol":"File","ExtendedVideoType":"None","ExtendedVideoSubType":"None","ExtendedVideoSubTypeDescription":"None","AttachmentSize":0,"SubtitleLocationType":"InternalStream"}],"Formats":[],"Bitrate":5675597,"RequiredHttpHeaders":{},"AddApiKeyToDirectStreamUrl":false,"ReadAtNativeFramerate":false,"ItemId":"15404"},"Chapters":[{"StartPositionTicks":0,"Name":"Chapter 01","MarkerType":"Chapter","ChapterIndex":0},{"StartPositionTicks":832070000,"Name":"Chapter 02","MarkerType":"Chapter","ChapterIndex":1},{"StartPositionTicks":5412900000,"Name":"Chapter 03","MarkerType":"Chapter","ChapterIndex":2},{"StartPositionTicks":6849740000,"Name":"Chapter 04","MarkerType":"Chapter","ChapterIndex":3},{"StartPositionTicks":11400130000,"Name":"Chapter 05","MarkerType":"Chapter","ChapterIndex":4},{"StartPositionTicks":14909470000,"Name":"Chapter 06","MarkerType":"Chapter","ChapterIndex":5},{"StartPositionTicks":18066380000,"Name":"Chapter 07","MarkerType":"Chapter","ChapterIndex":6},{"StartPositionTicks":19390620000,"Name":"Chapter 08","MarkerType":"Chapter","ChapterIndex":7},{"StartPositionTicks":22588810000,"Name":"Chapter 09","MarkerType":"Chapter","ChapterIndex":8},{"StartPositionTicks":29386850000,"Name":"Chapter 10","MarkerType":"Chapter","ChapterIndex":9},{"StartPositionTicks":30910040000,"Name":"Chapter 11","MarkerType":"Chapter","ChapterIndex":10},{"StartPositionTicks":32919970000,"Name":"Chapter 12","MarkerType":"Chapter","ChapterIndex":11},{"StartPositionTicks":37618830000,"Name":"Chapter 13","MarkerType":"Chapter","ChapterIndex":12},{"StartPositionTicks":41618660000,"Name":"Chapter 14","MarkerType":"Chapter","ChapterIndex":13},{"StartPositionTicks":46894340000,"Name":"Chapter 15","MarkerType":"Chapter","ChapterIndex":14},{"StartPositionTicks":54030220000,"Name":"Chapter 16","MarkerType":"Chapter","ChapterIndex":15},{"StartPositionTicks":63382900000,"Name":"Chapter 17","MarkerType":"Chapter","ChapterIndex":16},{"StartPositionTicks":66854700000,"Name":"Chapter 18","MarkerType":"Chapter","ChapterIndex":17},{"StartPositionTicks":72083260000,"Name":"Chapter 19","MarkerType":"Chapter","ChapterIndex":18},{"StartPositionTicks":77198370000,"Name":"Chapter 20","MarkerType":"Chapter","ChapterIndex":19}]}]