[{"MediaSourceInfo":{"Chapters":[],"Protocol":"File","Type":"Default","Container":"mp4","Size":1155197127,"Name":"暗河传.2025.S01E13.第13集.2160p.WEB-DL.H.265.10-bit.60fps","IsRemote":true,"HasMixedProtocols":false,"RunTimeTicks":23792560000,"SupportsTranscoding":true,"SupportsDirectStream":true,"SupportsDirectPlay":true,"IsInfiniteStream":false,"RequiresOpening":false,"RequiresClosing":false,"RequiresLooping":false,"SupportsProbing":true,"MediaStreams":[{"Codec":"hevc","CodecTag":"hev1","Language":"und","ColorTransfer":"bt709","ColorPrimaries":"bt709","ColorSpace":"bt709","TimeBase":"1/16000","VideoRange":"SDR","DisplayTitle":"4K HEVC","IsInterlaced":false,"BitRate":3612591,"BitDepth":10,"RefFrames":1,"IsDefault":true,"IsForced":false,"IsHearingImpaired":false,"Height":1608,"Width":3840,"AverageFrameRate":60.000008,"RealFrameRate":60,"Profile":"Main 10","Type":"Video","AspectRatio":"160:67","Index":0,"IsExternal":false,"IsTextSubtitleStream":false,"SupportsExternalStream":false,"Protocol":"File","PixelFormat":"yuv420p10le","Level":153,"IsAnamorphic":false,"ExtendedVideoType":"None","ExtendedVideoSubType":"None","ExtendedVideoSubTypeDescription":"None","AttachmentSize":0},{"Codec":"aac","CodecTag":"mp4a","Language":"chi","TimeBase":"1/44100","DisplayTitle":"Chinese AAC stereo (默认)","DisplayLanguage":"Chinese","IsInterlaced":false,"ChannelLayout":"stereo","BitRate":256000,"Channels":2,"SampleRate":44100,"IsDefault":true,"IsForced":false,"IsHearingImpaired":false,"Profile":"LC","Type":"Audio","Index":1,"IsExternal":false,"IsTextSubtitleStream":false,"SupportsExternalStream":false,"Protocol":"File","ExtendedVideoType":"None","ExtendedVideoSubType":"None","ExtendedVideoSubTypeDescription":"None","AttachmentSize":0}],"Formats":[],"Bitrate":3884229,"RequiredHttpHeaders":{},"AddApiKeyToDirectStreamUrl":false,"ReadAtNativeFramerate":false},"Chapters":[{"StartPositionTicks":0,"Name":"章节 1","MarkerType":"Chapter","ChapterIndex":0},{"StartPositionTicks":961200000,"Name":"章节 2","MarkerType":"Chapter","ChapterIndex":1},{"StartPositionTicks":4987880000,"Name":"苏喆替女考验，暮雨拒绝接近美色","MarkerType":"Chapter","ChapterIndex":2},{"StartPositionTicks":6675200000,"Name":"章节 4","MarkerType":"Chapter","ChapterIndex":3},{"StartPositionTicks":9926690000,"Name":"章节 5","MarkerType":"Chapter","ChapterIndex":4},{"StartPositionTicks":12049970000,"Name":"以指为剑！苏暮雨出绝招对战三官","MarkerType":"Chapter","ChapterIndex":5},{"StartPositionTicks":14924800000,"Name":"章节 7","MarkerType":"Chapter","ChapterIndex":6},{"StartPositionTicks":15573410000,"Name":"苏暮雨不敌三官，身中醉梦骨遭挟持","MarkerType":"Chapter","ChapterIndex":7},{"StartPositionTicks":17623340000,"Name":"章节 9","MarkerType":"Chapter","ChapterIndex":8},{"StartPositionTicks":20884970000,"Name":"苏暮雨被当筹码！昌河拔刀硬刚影宗","MarkerType":"Chapter","ChapterIndex":9},{"StartPositionTicks":22292400000,"Name":"章节 11","MarkerType":"Chapter","ChapterIndex":10}],"ZeroFingerprintConfidence":false}]