[{"MediaSourceInfo":{"Protocol":"File","Type":"Default","Container":"mkv","Size":4678305476,"Name":"浪客剑心.1996.S00E08.第8集.H.264","IsRemote":true,"HasMixedProtocols":false,"RunTimeTicks":27157150000,"SupportsTranscoding":true,"SupportsDirectStream":true,"SupportsDirectPlay":true,"IsInfiniteStream":false,"RequiresOpening":false,"RequiresClosing":false,"RequiresLooping":false,"SupportsProbing":false,"MediaStreams":[{"Codec":"h264","Language":"jpn","ColorSpace":"bt709","TimeBase":"1/1000","VideoRange":"SDR","DisplayTitle":"1080p H264","DisplayLanguage":"Japanese","NalLengthSize":"4","IsInterlaced":false,"BitRate":13781432,"BitDepth":10,"RefFrames":1,"IsDefault":true,"IsForced":false,"IsHearingImpaired":false,"Height":1080,"Width":1920,"AverageFrameRate":23.976025,"RealFrameRate":23.976025,"Profile":"High 10","Type":"Video","AspectRatio":"16:9","Index":0,"IsExternal":false,"IsTextSubtitleStream":false,"SupportsExternalStream":false,"Protocol":"File","PixelFormat":"yuv420p10le","Level":50,"IsAnamorphic":false,"ExtendedVideoType":"None","ExtendedVideoSubType":"None","ExtendedVideoSubTypeDescription":"None","AttachmentSize":0},{"Codec":"flac","Language":"jpn","TimeBase":"1/1000","DisplayTitle":"Japanese FLAC stereo (默认)","DisplayLanguage":"Japanese","IsInterlaced":false,"ChannelLayout":"stereo","BitDepth":24,"Channels":2,"SampleRate":48000,"IsDefault":true,"IsForced":false,"IsHearingImpaired":false,"Type":"Audio","Index":1,"IsExternal":false,"IsTextSubtitleStream":false,"SupportsExternalStream":false,"Protocol":"File","ExtendedVideoType":"None","ExtendedVideoSubType":"None","ExtendedVideoSubTypeDescription":"None","AttachmentSize":0},{"Codec":"flac","Language":"jpn","TimeBase":"1/1000","DisplayTitle":"Japanese FLAC 5.1","DisplayLanguage":"Japanese","IsInterlaced":false,"ChannelLayout":"5.1","BitDepth":24,"Channels":6,"SampleRate":48000,"IsDefault":false,"IsForced":false,"IsHearingImpaired":false,"Type":"Audio","Index":2,"IsExternal":false,"IsTextSubtitleStream":false,"SupportsExternalStream":false,"Protocol":"File","ExtendedVideoType":"None","ExtendedVideoSubType":"None","ExtendedVideoSubTypeDescription":"None","AttachmentSize":0}],"Formats":[],"Bitrate":13781432,"RequiredHttpHeaders":{},"AddApiKeyToDirectStreamUrl":false,"ReadAtNativeFramerate":false},"Chapters":[{"StartPositionTicks":0,"Name":"臨戰","MarkerType":"Chapter","ChapterIndex":0},{"StartPositionTicks":1679180000,"Name":"大阪へ","MarkerType":"Chapter","ChapterIndex":1},{"StartPositionTicks":3628620000,"Name":"決意","MarkerType":"Chapter","ChapterIndex":2},{"StartPositionTicks":7434930000,"Name":"信念","MarkerType":"Chapter","ChapterIndex":3},{"StartPositionTicks":12301040000,"Name":"葵屋の攻防","MarkerType":"Chapter","ChapterIndex":4},{"StartPositionTicks":14881120000,"Name":"宗次郎再び","MarkerType":"Chapter","ChapterIndex":5},{"StartPositionTicks":18721200000,"Name":"決戰","MarkerType":"Chapter","ChapterIndex":6},{"StartPositionTicks":23821300000,"Name":"ただいま","MarkerType":"Chapter","ChapterIndex":7},{"StartPositionTicks":25445420000,"Name":"エンディング","MarkerType":"Chapter","ChapterIndex":8}],"ZeroFingerprintConfidence":false}]