[{"MediaSourceInfo":{"Protocol":"File","Type":"Default","Container":"mkv","Size":8289733189,"Name":"以法之名.2025.S01E06.第6集.2160p.WEB-DL.HQ.H.265.60fps","IsRemote":true,"HasMixedProtocols":false,"RunTimeTicks":27776960000,"SupportsTranscoding":true,"SupportsDirectStream":true,"SupportsDirectPlay":true,"IsInfiniteStream":false,"RequiresOpening":false,"RequiresClosing":false,"RequiresLooping":false,"SupportsProbing":false,"MediaStreams":[{"Codec":"hevc","Language":"chi","ColorTransfer":"bt709","ColorPrimaries":"bt709","ColorSpace":"bt709","TimeBase":"1/1000","Title":"Mandarin [AAC2.0]","VideoRange":"SDR","DisplayTitle":"4K HEVC","DisplayLanguage":"Chinese Simplified","IsInterlaced":false,"BitRate":23875134,"BitDepth":10,"RefFrames":1,"IsDefault":true,"IsForced":false,"IsHearingImpaired":false,"Height":1608,"Width":3840,"AverageFrameRate":60,"RealFrameRate":60,"Profile":"Main 10","Type":"Video","AspectRatio":"160:67","Index":0,"IsExternal":false,"IsTextSubtitleStream":false,"SupportsExternalStream":false,"Protocol":"File","PixelFormat":"yuv420p10le","Level":153,"IsAnamorphic":false,"ExtendedVideoType":"None","ExtendedVideoSubType":"None","ExtendedVideoSubTypeDescription":"None","AttachmentSize":0},{"Codec":"dts","Language":"chi","TimeBase":"1/1000","Title":"Mandarin [DTS.5.1]","DisplayTitle":"Chinese Simplified DTS 5.1 (默认)","DisplayLanguage":"Chinese Simplified","IsInterlaced":false,"ChannelLayout":"5.1","BitRate":768000,"Channels":6,"SampleRate":48000,"IsDefault":true,"IsForced":false,"IsHearingImpaired":false,"Profile":"DTS","Type":"Audio","Index":1,"IsExternal":false,"IsTextSubtitleStream":false,"SupportsExternalStream":false,"Protocol":"File","ExtendedVideoType":"None","ExtendedVideoSubType":"None","ExtendedVideoSubTypeDescription":"None","AttachmentSize":0},{"Codec":"eac3","Language":"chi","TimeBase":"1/1000","Title":"Mandarin [DDP.5.1]","DisplayTitle":"Chinese Simplified EAC3 5.1","DisplayLanguage":"Chinese Simplified","IsInterlaced":false,"ChannelLayout":"5.1","BitRate":448000,"Channels":6,"SampleRate":48000,"IsDefault":false,"IsForced":false,"IsHearingImpaired":false,"Type":"Audio","Index":2,"IsExternal":false,"IsTextSubtitleStream":false,"SupportsExternalStream":false,"Protocol":"File","ExtendedVideoType":"None","ExtendedVideoSubType":"None","ExtendedVideoSubTypeDescription":"None","AttachmentSize":0},{"Codec":"aac","Language":"chi","TimeBase":"1/1000","Title":"Mandarin [AAC.2.0]","DisplayTitle":"Chinese Simplified AAC stereo","DisplayLanguage":"Chinese Simplified","IsInterlaced":false,"ChannelLayout":"stereo","BitRate":192000,"Channels":2,"SampleRate":44100,"IsDefault":false,"IsForced":false,"IsHearingImpaired":false,"Profile":"LC","Type":"Audio","Index":3,"IsExternal":false,"IsTextSubtitleStream":false,"SupportsExternalStream":false,"Protocol":"File","ExtendedVideoType":"None","ExtendedVideoSubType":"None","ExtendedVideoSubTypeDescription":"None","AttachmentSize":0},{"Codec":"srt","Language":"zh-CN","DisplayTitle":"Chinese Simplified (SRT)","DisplayLanguage":"Chinese Simplified","IsInterlaced":false,"IsDefault":false,"IsForced":false,"IsHearingImpaired":false,"Type":"Subtitle","Index":4,"IsExternal":true,"IsTextSubtitleStream":true,"SupportsExternalStream":true,"Path":"以法之名.2025.S01E06.第6集.2160p.WEB-DL.HQ.H.265.60fps.zh-CN.srt","Protocol":"File","ExtendedVideoType":"None","ExtendedVideoSubType":"None","ExtendedVideoSubTypeDescription":"None","AttachmentSize":0}],"Formats":[],"Bitrate":23875134,"RequiredHttpHeaders":{},"AddApiKeyToDirectStreamUrl":false,"ReadAtNativeFramerate":false},"Chapters":[{"StartPositionTicks":0,"Name":"IntroStart#SA","MarkerType":"IntroStart","ChapterIndex":0},{"StartPositionTicks":1300000000,"Name":"IntroEnd#SA","MarkerType":"IntroEnd","ChapterIndex":1},{"StartPositionTicks":3432760000,"Name":"洪亮愤怒质问，李人骏无奈告知内情","MarkerType":"Chapter","ChapterIndex":2},{"StartPositionTicks":18135350000,"Name":"张文菁反常认罪，郑雅萍难以置信","MarkerType":"Chapter","ChapterIndex":3},{"StartPositionTicks":20301190000,"Name":"郑雅萍心存疑虑，决定留下继续调查","MarkerType":"Chapter","ChapterIndex":4},{"StartPositionTicks":23281130000,"Name":"周彪检举乔振兴受贿，讲述具体细节","MarkerType":"Chapter","ChapterIndex":5},{"StartPositionTicks":26906732406,"Name":"CreditsStart#SA","MarkerType":"CreditsStart","ChapterIndex":6}],"ZeroFingerprintConfidence":false}]