[{"MediaSourceInfo":{"Chapters":[],"Protocol":"File","Type":"Default","Container":"mkv","Size":2572128197,"Name":"迷尸校园.2025.S01E05.第5集.1080p.Netflix.WEB-DL.H.264-HiveWeb","IsRemote":true,"HasMixedProtocols":false,"RunTimeTicks":32873280000,"SupportsTranscoding":true,"SupportsDirectStream":true,"SupportsDirectPlay":true,"IsInfiniteStream":false,"RequiresOpening":false,"RequiresClosing":false,"RequiresLooping":false,"SupportsProbing":true,"MediaStreams":[{"Codec":"h264","TimeBase":"1/1000","VideoRange":"SDR","DisplayTitle":"1080p H264","NalLengthSize":"4","IsInterlaced":false,"BitRate":6259498,"BitDepth":8,"RefFrames":1,"IsDefault":true,"IsForced":false,"IsHearingImpaired":false,"Height":1080,"Width":1920,"AverageFrameRate":25,"RealFrameRate":25,"Profile":"High","Type":"Video","AspectRatio":"16:9","Index":0,"IsExternal":false,"IsTextSubtitleStream":false,"SupportsExternalStream":false,"Protocol":"File","PixelFormat":"yuv420p","Level":40,"IsAnamorphic":false,"ExtendedVideoType":"None","ExtendedVideoSubType":"None","ExtendedVideoSubTypeDescription":"None","AttachmentSize":0},{"Codec":"eac3","Language":"tha","TimeBase":"1/1000","DisplayTitle":"Thai EAC3 5.1 (默认)","DisplayLanguage":"Thai","IsInterlaced":false,"ChannelLayout":"5.1","BitRate":768000,"Channels":6,"SampleRate":48000,"IsDefault":true,"IsForced":false,"IsHearingImpaired":false,"Type":"Audio","Index":1,"IsExternal":false,"IsTextSubtitleStream":false,"SupportsExternalStream":false,"Protocol":"File","ExtendedVideoType":"None","ExtendedVideoSubType":"None","ExtendedVideoSubTypeDescription":"None","AttachmentSize":0},{"Codec":"subrip","Language":"tha","TimeBase":"1/1000","Title":"SDH","DisplayTitle":"Thai (SUBRIP)","DisplayLanguage":"Thai","IsInterlaced":false,"IsDefault":false,"IsForced":false,"IsHearingImpaired":false,"Type":"Subtitle","Index":2,"IsExternal":false,"IsTextSubtitleStream":true,"SupportsExternalStream":true,"Protocol":"File","ExtendedVideoType":"None","ExtendedVideoSubType":"None","ExtendedVideoSubTypeDescription":"None","AttachmentSize":0,"SubtitleLocationType":"InternalStream"},{"Codec":"subrip","Language":"chi","TimeBase":"1/1000","Title":"Traditional","DisplayTitle":"Chinese Traditional (SUBRIP)","DisplayLanguage":"Chinese Traditional","IsInterlaced":false,"IsDefault":false,"IsForced":false,"IsHearingImpaired":false,"Type":"Subtitle","Index":3,"IsExternal":false,"IsTextSubtitleStream":true,"SupportsExternalStream":true,"Protocol":"File","ExtendedVideoType":"None","ExtendedVideoSubType":"None","ExtendedVideoSubTypeDescription":"None","AttachmentSize":0,"SubtitleLocationType":"InternalStream"}],"Formats":[],"Bitrate":6259498,"RequiredHttpHeaders":{},"AddApiKeyToDirectStreamUrl":false,"ReadAtNativeFramerate":false},"Chapters":[{"StartPositionTicks":0,"Name":"Part 01","MarkerType":"Chapter","ChapterIndex":0},{"StartPositionTicks":3415000000,"Name":"Intro","MarkerType":"Chapter","ChapterIndex":1},{"StartPositionTicks":4272500000,"Name":"Part 02","MarkerType":"Chapter","ChapterIndex":2},{"StartPositionTicks":30094500000,"Name":"Credits","MarkerType":"Chapter","ChapterIndex":3}],"ZeroFingerprintConfidence":false}]