[{"MediaSourceInfo":{"Chapters":[],"Protocol":"File","Type":"Default","Container":"mkv","Size":5188042945,"Name":"我的青春.2025.S01E06.第6集.1080p.WEB-DL.H.264","IsRemote":true,"HasMixedProtocols":false,"RunTimeTicks":42291910000,"SupportsTranscoding":true,"SupportsDirectStream":true,"SupportsDirectPlay":true,"IsInfiniteStream":false,"RequiresOpening":false,"RequiresClosing":false,"RequiresLooping":false,"SupportsProbing":true,"MediaStreams":[{"Codec":"h264","Language":"kor","TimeBase":"1/1000","VideoRange":"SDR","DisplayTitle":"1080p H264","DisplayLanguage":"Korean","NalLengthSize":"4","IsInterlaced":false,"BitRate":9813778,"BitDepth":8,"RefFrames":1,"IsDefault":true,"IsForced":false,"IsHearingImpaired":false,"Height":1080,"Width":1920,"AverageFrameRate":29.97003,"RealFrameRate":29.97003,"Profile":"High","Type":"Video","AspectRatio":"16:9","Index":0,"IsExternal":false,"IsTextSubtitleStream":false,"SupportsExternalStream":false,"Protocol":"File","PixelFormat":"yuv420p","Level":41,"IsAnamorphic":false,"ExtendedVideoType":"None","ExtendedVideoSubType":"None","ExtendedVideoSubTypeDescription":"None","AttachmentSize":0},{"Codec":"aac","Language":"kor","TimeBase":"1/1000","DisplayTitle":"Korean AAC stereo (默认)","DisplayLanguage":"Korean","IsInterlaced":false,"ChannelLayout":"stereo","BitRate":192000,"Channels":2,"SampleRate":48000,"IsDefault":true,"IsForced":false,"IsHearingImpaired":false,"Profile":"LC","Type":"Audio","Index":1,"IsExternal":false,"IsTextSubtitleStream":false,"SupportsExternalStream":false,"Protocol":"File","ExtendedVideoType":"None","ExtendedVideoSubType":"None","ExtendedVideoSubTypeDescription":"None","AttachmentSize":0},{"Codec":"subrip","Language":"chi","TimeBase":"1/1000","Title":"Simplified","DisplayTitle":"Chinese Simplified (默认 SUBRIP)","DisplayLanguage":"Chinese Simplified","IsInterlaced":false,"IsDefault":true,"IsForced":false,"IsHearingImpaired":false,"Type":"Subtitle","Index":2,"IsExternal":false,"IsTextSubtitleStream":true,"SupportsExternalStream":true,"Protocol":"File","ExtendedVideoType":"None","ExtendedVideoSubType":"None","ExtendedVideoSubTypeDescription":"None","AttachmentSize":0,"SubtitleLocationType":"InternalStream"},{"Codec":"subrip","Language":"chi","TimeBase":"1/1000","Title":"Traditional","DisplayTitle":"Chinese Traditional (SUBRIP)","DisplayLanguage":"Chinese Traditional","IsInterlaced":false,"IsDefault":false,"IsForced":false,"IsHearingImpaired":false,"Type":"Subtitle","Index":3,"IsExternal":false,"IsTextSubtitleStream":true,"SupportsExternalStream":true,"Protocol":"File","ExtendedVideoType":"None","ExtendedVideoSubType":"None","ExtendedVideoSubTypeDescription":"None","AttachmentSize":0,"SubtitleLocationType":"InternalStream"}],"Formats":[],"Bitrate":9813778,"RequiredHttpHeaders":{},"AddApiKeyToDirectStreamUrl":false,"ReadAtNativeFramerate":false},"Chapters":[{"StartPositionTicks":0,"Name":"Start","MarkerType":"Chapter","ChapterIndex":0},{"StartPositionTicks":510000000,"Name":"Header","MarkerType":"Chapter","ChapterIndex":1},{"StartPositionTicks":41320000000,"Name":"Tailer","MarkerType":"Chapter","ChapterIndex":2}],"ZeroFingerprintConfidence":false}]