[{"MediaSourceInfo":{"Chapters":[],"Protocol":"File","Type":"Default","Container":"mkv","Size":3488289721,"Name":"我的邻居山田君 (1999) - 1080p.H.265","IsRemote":true,"HasMixedProtocols":false,"RunTimeTicks":62202560000,"SupportsTranscoding":true,"SupportsDirectStream":true,"SupportsDirectPlay":true,"IsInfiniteStream":false,"RequiresOpening":false,"RequiresClosing":false,"RequiresLooping":false,"SupportsProbing":true,"MediaStreams":[{"Codec":"hevc","ColorPrimaries":"bt709","TimeBase":"1/1000","VideoRange":"SDR","DisplayTitle":"1080p HEVC","IsInterlaced":false,"BitRate":4486361,"BitDepth":10,"RefFrames":1,"IsDefault":true,"IsForced":false,"IsHearingImpaired":false,"Height":1038,"Width":1920,"AverageFrameRate":23.976025,"RealFrameRate":23.976025,"Profile":"Main 10","Type":"Video","AspectRatio":"320:173","Index":0,"IsExternal":false,"IsTextSubtitleStream":false,"SupportsExternalStream":false,"Protocol":"File","PixelFormat":"yuv420p10le","Level":120,"IsAnamorphic":false,"ExtendedVideoType":"None","ExtendedVideoSubType":"None","ExtendedVideoSubTypeDescription":"None","AttachmentSize":0},{"Codec":"ac3","Language":"jpn","TimeBase":"1/1000","DisplayTitle":"Japanese AC3 5.1 (默认)","DisplayLanguage":"Japanese","IsInterlaced":false,"ChannelLayout":"5.1","BitRate":640000,"Channels":6,"SampleRate":48000,"IsDefault":true,"IsForced":false,"IsHearingImpaired":false,"Type":"Audio","Index":1,"IsExternal":false,"IsTextSubtitleStream":false,"SupportsExternalStream":false,"Protocol":"File","ExtendedVideoType":"None","ExtendedVideoSubType":"None","ExtendedVideoSubTypeDescription":"None","AttachmentSize":0},{"Codec":"ac3","Language":"eng","TimeBase":"1/1000","DisplayTitle":"English AC3 5.1","DisplayLanguage":"English","IsInterlaced":false,"ChannelLayout":"5.1","BitRate":640000,"Channels":6,"SampleRate":48000,"IsDefault":false,"IsForced":false,"IsHearingImpaired":false,"Type":"Audio","Index":2,"IsExternal":false,"IsTextSubtitleStream":false,"SupportsExternalStream":false,"Protocol":"File","ExtendedVideoType":"None","ExtendedVideoSubType":"None","ExtendedVideoSubTypeDescription":"None","AttachmentSize":0},{"Codec":"ac3","Language":"chi","TimeBase":"1/1000","DisplayTitle":"Chinese AC3 stereo","DisplayLanguage":"Chinese","IsInterlaced":false,"ChannelLayout":"stereo","BitRate":192000,"Channels":2,"SampleRate":48000,"IsDefault":false,"IsForced":false,"IsHearingImpaired":false,"Type":"Audio","Index":3,"IsExternal":false,"IsTextSubtitleStream":false,"SupportsExternalStream":false,"Protocol":"File","ExtendedVideoType":"None","ExtendedVideoSubType":"None","ExtendedVideoSubTypeDescription":"None","AttachmentSize":0},{"Codec":"PGSSUB","Language":"jpn","TimeBase":"1/1000","DisplayTitle":"Japanese (默认 PGSSUB)","DisplayLanguage":"Japanese","IsInterlaced":false,"IsDefault":true,"IsForced":false,"IsHearingImpaired":false,"Type":"Subtitle","Index":4,"IsExternal":false,"IsTextSubtitleStream":false,"SupportsExternalStream":false,"Protocol":"File","ExtendedVideoType":"None","ExtendedVideoSubType":"None","ExtendedVideoSubTypeDescription":"None","AttachmentSize":0,"SubtitleLocationType":"InternalStream"},{"Codec":"PGSSUB","Language":"eng","TimeBase":"1/1000","DisplayTitle":"English (PGSSUB)","DisplayLanguage":"English","IsInterlaced":false,"IsDefault":false,"IsForced":false,"IsHearingImpaired":false,"Type":"Subtitle","Index":5,"IsExternal":false,"IsTextSubtitleStream":false,"SupportsExternalStream":false,"Protocol":"File","ExtendedVideoType":"None","ExtendedVideoSubType":"None","ExtendedVideoSubTypeDescription":"None","AttachmentSize":0,"SubtitleLocationType":"InternalStream"},{"Codec":"PGSSUB","Language":"chi","TimeBase":"1/1000","DisplayTitle":"Chinese (PGSSUB)","DisplayLanguage":"Chinese","IsInterlaced":false,"IsDefault":false,"IsForced":false,"IsHearingImpaired":false,"Type":"Subtitle","Index":6,"IsExternal":false,"IsTextSubtitleStream":false,"SupportsExternalStream":false,"Protocol":"File","ExtendedVideoType":"None","ExtendedVideoSubType":"None","ExtendedVideoSubTypeDescription":"None","AttachmentSize":0,"SubtitleLocationType":"InternalStream"},{"Codec":"ass","Language":"zh-CN","Title":"1","DisplayTitle":"Chinese Simplified (ASS)","DisplayLanguage":"Chinese Simplified","IsInterlaced":false,"IsDefault":false,"IsForced":false,"IsHearingImpaired":false,"Type":"Subtitle","Index":7,"IsExternal":true,"IsTextSubtitleStream":true,"SupportsExternalStream":true,"Path":"我的邻居山田君 (1999) - 1080p.H.265.1.zh-CN.ass","Protocol":"File","ExtendedVideoType":"None","ExtendedVideoSubType":"None","ExtendedVideoSubTypeDescription":"None","AttachmentSize":0},{"Codec":"ass","Language":"zh-CN","Title":"2","DisplayTitle":"Chinese Simplified (ASS)","DisplayLanguage":"Chinese Simplified","IsInterlaced":false,"IsDefault":false,"IsForced":false,"IsHearingImpaired":false,"Type":"Subtitle","Index":8,"IsExternal":true,"IsTextSubtitleStream":true,"SupportsExternalStream":true,"Path":"我的邻居山田君 (1999) - 1080p.H.265.2.zh-CN.ass","Protocol":"File","ExtendedVideoType":"None","ExtendedVideoSubType":"None","ExtendedVideoSubTypeDescription":"None","AttachmentSize":0},{"Codec":"ass","Language":"zh-CN","Title":"3","DisplayTitle":"Chinese Simplified (ASS)","DisplayLanguage":"Chinese Simplified","IsInterlaced":false,"IsDefault":false,"IsForced":false,"IsHearingImpaired":false,"Type":"Subtitle","Index":9,"IsExternal":true,"IsTextSubtitleStream":true,"SupportsExternalStream":true,"Path":"我的邻居山田君 (1999) - 1080p.H.265.3.zh-CN.ass","Protocol":"File","ExtendedVideoType":"None","ExtendedVideoSubType":"None","ExtendedVideoSubTypeDescription":"None","AttachmentSize":0},{"Codec":"ass","Language":"zh-CN","Title":"4","DisplayTitle":"Chinese Simplified (ASS)","DisplayLanguage":"Chinese Simplified","IsInterlaced":false,"IsDefault":false,"IsForced":false,"IsHearingImpaired":false,"Type":"Subtitle","Index":10,"IsExternal":true,"IsTextSubtitleStream":true,"SupportsExternalStream":true,"Path":"我的邻居山田君 (1999) - 1080p.H.265.4.zh-CN.ass","Protocol":"File","ExtendedVideoType":"None","ExtendedVideoSubType":"None","ExtendedVideoSubTypeDescription":"None","AttachmentSize":0},{"Codec":"ass","Language":"zh-CN","Title":"5","DisplayTitle":"Chinese Simplified (ASS)","DisplayLanguage":"Chinese Simplified","IsInterlaced":false,"IsDefault":false,"IsForced":false,"IsHearingImpaired":false,"Type":"Subtitle","Index":11,"IsExternal":true,"IsTextSubtitleStream":true,"SupportsExternalStream":true,"Path":"我的邻居山田君 (1999) - 1080p.H.265.5.zh-CN.ass","Protocol":"File","ExtendedVideoType":"None","ExtendedVideoSubType":"None","ExtendedVideoSubTypeDescription":"None","AttachmentSize":0},{"Codec":"ass","Language":"zh-CN","Title":"6","DisplayTitle":"Chinese Simplified (ASS)","DisplayLanguage":"Chinese Simplified","IsInterlaced":false,"IsDefault":false,"IsForced":false,"IsHearingImpaired":false,"Type":"Subtitle","Index":12,"IsExternal":true,"IsTextSubtitleStream":true,"SupportsExternalStream":true,"Path":"我的邻居山田君 (1999) - 1080p.H.265.6.zh-CN.ass","Protocol":"File","ExtendedVideoType":"None","ExtendedVideoSubType":"None","ExtendedVideoSubTypeDescription":"None","AttachmentSize":0},{"Codec":"ass","Language":"zh-CN","Title":"7","DisplayTitle":"Chinese Simplified (ASS)","DisplayLanguage":"Chinese Simplified","IsInterlaced":false,"IsDefault":false,"IsForced":false,"IsHearingImpaired":false,"Type":"Subtitle","Index":13,"IsExternal":true,"IsTextSubtitleStream":true,"SupportsExternalStream":true,"Path":"我的邻居山田君 (1999) - 1080p.H.265.7.zh-CN.ass","Protocol":"File","ExtendedVideoType":"None","ExtendedVideoSubType":"None","ExtendedVideoSubTypeDescription":"None","AttachmentSize":0},{"Codec":"ass","Language":"zh-CN","Title":"8","DisplayTitle":"Chinese Simplified (ASS)","DisplayLanguage":"Chinese Simplified","IsInterlaced":false,"IsDefault":false,"IsForced":false,"IsHearingImpaired":false,"Type":"Subtitle","Index":14,"IsExternal":true,"IsTextSubtitleStream":true,"SupportsExternalStream":true,"Path":"我的邻居山田君 (1999) - 1080p.H.265.8.zh-CN.ass","Protocol":"File","ExtendedVideoType":"None","ExtendedVideoSubType":"None","ExtendedVideoSubTypeDescription":"None","AttachmentSize":0},{"Codec":"ass","Language":"zh-CN","Title":"9","DisplayTitle":"Chinese Simplified (ASS)","DisplayLanguage":"Chinese Simplified","IsInterlaced":false,"IsDefault":false,"IsForced":false,"IsHearingImpaired":false,"Type":"Subtitle","Index":15,"IsExternal":true,"IsTextSubtitleStream":true,"SupportsExternalStream":true,"Path":"我的邻居山田君 (1999) - 1080p.H.265.9.zh-CN.ass","Protocol":"File","ExtendedVideoType":"None","ExtendedVideoSubType":"None","ExtendedVideoSubTypeDescription":"None","AttachmentSize":0},{"Codec":"ass","Language":"zh-CN","Title":"10","DisplayTitle":"Chinese Simplified (ASS)","DisplayLanguage":"Chinese Simplified","IsInterlaced":false,"IsDefault":false,"IsForced":false,"IsHearingImpaired":false,"Type":"Subtitle","Index":16,"IsExternal":true,"IsTextSubtitleStream":true,"SupportsExternalStream":true,"Path":"我的邻居山田君 (1999) - 1080p.H.265.10.zh-CN.ass","Protocol":"File","ExtendedVideoType":"None","ExtendedVideoSubType":"None","ExtendedVideoSubTypeDescription":"None","AttachmentSize":0},{"Codec":"ass","Language":"zh-CN","DisplayTitle":"Chinese Simplified (ASS)","DisplayLanguage":"Chinese Simplified","IsInterlaced":false,"IsDefault":false,"IsForced":false,"IsHearingImpaired":false,"Type":"Subtitle","Index":17,"IsExternal":true,"IsTextSubtitleStream":true,"SupportsExternalStream":true,"Path":"我的邻居山田君 (1999) - 1080p.H.265.zh-CN.ass","Protocol":"File","ExtendedVideoType":"None","ExtendedVideoSubType":"None","ExtendedVideoSubTypeDescription":"None","AttachmentSize":0}],"Formats":[],"Bitrate":4486361,"RequiredHttpHeaders":{},"AddApiKeyToDirectStreamUrl":false,"ReadAtNativeFramerate":false},"Chapters":[{"StartPositionTicks":0,"Name":"Chapter 01","MarkerType":"Chapter","ChapterIndex":0},{"StartPositionTicks":130130000,"Name":"Chapter 02","MarkerType":"Chapter","ChapterIndex":1},{"StartPositionTicks":500500000,"Name":"Chapter 03","MarkerType":"Chapter","ChapterIndex":2},{"StartPositionTicks":932180000,"Name":"Chapter 04","MarkerType":"Chapter","ChapterIndex":3},{"StartPositionTicks":1432680000,"Name":"Chapter 05","MarkerType":"Chapter","ChapterIndex":4},{"StartPositionTicks":1867690000,"Name":"Chapter 06","MarkerType":"Chapter","ChapterIndex":5},{"StartPositionTicks":1947770000,"Name":"Chapter 07","MarkerType":"Chapter","ChapterIndex":6},{"StartPositionTicks":2877040000,"Name":"Chapter 08","MarkerType":"Chapter","ChapterIndex":7},{"StartPositionTicks":5340330000,"Name":"Chapter 09","MarkerType":"Chapter","ChapterIndex":8},{"StartPositionTicks":5779100000,"Name":"Chapter 10","MarkerType":"Chapter","ChapterIndex":9},{"StartPositionTicks":6874780000,"Name":"Chapter 11","MarkerType":"Chapter","ChapterIndex":10},{"StartPositionTicks":7105010000,"Name":"Chapter 12","MarkerType":"Chapter","ChapterIndex":11},{"StartPositionTicks":13428830000,"Name":"Chapter 13","MarkerType":"Chapter","ChapterIndex":12},{"StartPositionTicks":13601500000,"Name":"Chapter 14","MarkerType":"Chapter","ChapterIndex":13},{"StartPositionTicks":14029430000,"Name":"Chapter 15","MarkerType":"Chapter","ChapterIndex":14},{"StartPositionTicks":14409810000,"Name":"Chapter 16","MarkerType":"Chapter","ChapterIndex":15},{"StartPositionTicks":15022500000,"Name":"Chapter 17","MarkerType":"Chapter","ChapterIndex":16},{"StartPositionTicks":15377860000,"Name":"Chapter 18","MarkerType":"Chapter","ChapterIndex":17},{"StartPositionTicks":15716530000,"Name":"Chapter 19","MarkerType":"Chapter","ChapterIndex":18},{"StartPositionTicks":16005570000,"Name":"Chapter 20","MarkerType":"Chapter","ChapterIndex":19},{"StartPositionTicks":16415140000,"Name":"Chapter 21","MarkerType":"Chapter","ChapterIndex":20},{"StartPositionTicks":16736710000,"Name":"Chapter 22","MarkerType":"Chapter","ChapterIndex":21},{"StartPositionTicks":16918560000,"Name":"Chapter 23","MarkerType":"Chapter","ChapterIndex":22},{"StartPositionTicks":17295190000,"Name":"Chapter 24","MarkerType":"Chapter","ChapterIndex":23},{"StartPositionTicks":17516240000,"Name":"Chapter 25","MarkerType":"Chapter","ChapterIndex":24},{"StartPositionTicks":18083890000,"Name":"Chapter 26","MarkerType":"Chapter","ChapterIndex":25},{"StartPositionTicks":19151630000,"Name":"Chapter 27","MarkerType":"Chapter","ChapterIndex":26},{"StartPositionTicks":19627520000,"Name":"Chapter 28","MarkerType":"Chapter","ChapterIndex":27},{"StartPositionTicks":20443750000,"Name":"Chapter 29","MarkerType":"Chapter","ChapterIndex":28},{"StartPositionTicks":20944250000,"Name":"Chapter 30","MarkerType":"Chapter","ChapterIndex":29},{"StartPositionTicks":21351320000,"Name":"Chapter 31","MarkerType":"Chapter","ChapterIndex":30},{"StartPositionTicks":21920220000,"Name":"Chapter 32","MarkerType":"Chapter","ChapterIndex":31},{"StartPositionTicks":22226360000,"Name":"Chapter 33","MarkerType":"Chapter","ChapterIndex":32},{"StartPositionTicks":22441580000,"Name":"Chapter 34","MarkerType":"Chapter","ChapterIndex":33},{"StartPositionTicks":23227360000,"Name":"Chapter 35","MarkerType":"Chapter","ChapterIndex":34},{"StartPositionTicks":24810190000,"Name":"Chapter 36","MarkerType":"Chapter","ChapterIndex":35},{"StartPositionTicks":25218100000,"Name":"Chapter 37","MarkerType":"Chapter","ChapterIndex":36},{"StartPositionTicks":25528410000,"Name":"Chapter 38","MarkerType":"Chapter","ChapterIndex":37},{"StartPositionTicks":26711260000,"Name":"Chapter 39","MarkerType":"Chapter","ChapterIndex":38},{"StartPositionTicks":27078290000,"Name":"Chapter 40","MarkerType":"Chapter","ChapterIndex":39},{"StartPositionTicks":27850730000,"Name":"Chapter 41","MarkerType":"Chapter","ChapterIndex":40},{"StartPositionTicks":28224020000,"Name":"Chapter 42","MarkerType":"Chapter","ChapterIndex":41},{"StartPositionTicks":28658210000,"Name":"Chapter 43","MarkerType":"Chapter","ChapterIndex":42},{"StartPositionTicks":28868000000,"Name":"Chapter 44","MarkerType":"Chapter","ChapterIndex":43},{"StartPositionTicks":29078210000,"Name":"Chapter 45","MarkerType":"Chapter","ChapterIndex":44},{"StartPositionTicks":29456090000,"Name":"Chapter 46","MarkerType":"Chapter","ChapterIndex":45},{"StartPositionTicks":29991620000,"Name":"Chapter 47","MarkerType":"Chapter","ChapterIndex":46},{"StartPositionTicks":30422470000,"Name":"Chapter 48","MarkerType":"Chapter","ChapterIndex":47},{"StartPositionTicks":30567610000,"Name":"Chapter 49","MarkerType":"Chapter","ChapterIndex":48},{"StartPositionTicks":31399690000,"Name":"Chapter 50","MarkerType":"Chapter","ChapterIndex":49},{"StartPositionTicks":31897690000,"Name":"Chapter 51","MarkerType":"Chapter","ChapterIndex":50},{"StartPositionTicks":32306850000,"Name":"Chapter 52","MarkerType":"Chapter","ChapterIndex":51},{"StartPositionTicks":32693070000,"Name":"Chapter 53","MarkerType":"Chapter","ChapterIndex":52},{"StartPositionTicks":33924720000,"Name":"Chapter 54","MarkerType":"Chapter","ChapterIndex":53},{"StartPositionTicks":34264220000,"Name":"Chapter 55","MarkerType":"Chapter","ChapterIndex":54},{"StartPositionTicks":34950320000,"Name":"Chapter 56","MarkerType":"Chapter","ChapterIndex":55},{"StartPositionTicks":35334460000,"Name":"Chapter 57","MarkerType":"Chapter","ChapterIndex":56},{"StartPositionTicks":35795330000,"Name":"Chapter 58","MarkerType":"Chapter","ChapterIndex":57},{"StartPositionTicks":36384260000,"Name":"Chapter 59","MarkerType":"Chapter","ChapterIndex":58},{"StartPositionTicks":36667460000,"Name":"Chapter 60","MarkerType":"Chapter","ChapterIndex":59},{"StartPositionTicks":36955240000,"Name":"Chapter 61","MarkerType":"Chapter","ChapterIndex":60},{"StartPositionTicks":37416540000,"Name":"Chapter 62","MarkerType":"Chapter","ChapterIndex":61},{"StartPositionTicks":37774810000,"Name":"Chapter 63","MarkerType":"Chapter","ChapterIndex":62},{"StartPositionTicks":38156440000,"Name":"Chapter 64","MarkerType":"Chapter","ChapterIndex":63},{"StartPositionTicks":38683220000,"Name":"Chapter 65","MarkerType":"Chapter","ChapterIndex":64},{"StartPositionTicks":40107140000,"Name":"Chapter 66","MarkerType":"Chapter","ChapterIndex":65},{"StartPositionTicks":41818850000,"Name":"Chapter 67","MarkerType":"Chapter","ChapterIndex":66},{"StartPositionTicks":42047830000,"Name":"Chapter 68","MarkerType":"Chapter","ChapterIndex":67},{"StartPositionTicks":42368150000,"Name":"Chapter 69","MarkerType":"Chapter","ChapterIndex":68},{"StartPositionTicks":42716000000,"Name":"Chapter 70","MarkerType":"Chapter","ChapterIndex":69},{"StartPositionTicks":43292820000,"Name":"Chapter 71","MarkerType":"Chapter","ChapterIndex":70},{"StartPositionTicks":44032310000,"Name":"Chapter 72","MarkerType":"Chapter","ChapterIndex":71},{"StartPositionTicks":44431040000,"Name":"Chapter 73","MarkerType":"Chapter","ChapterIndex":72},{"StartPositionTicks":49052740000,"Name":"Chapter 74","MarkerType":"Chapter","ChapterIndex":73},{"StartPositionTicks":51471410000,"Name":"Chapter 75","MarkerType":"Chapter","ChapterIndex":74},{"StartPositionTicks":51732920000,"Name":"Chapter 76","MarkerType":"Chapter","ChapterIndex":75},{"StartPositionTicks":52013200000,"Name":"Chapter 77","MarkerType":"Chapter","ChapterIndex":76},{"StartPositionTicks":52349370000,"Name":"Chapter 78","MarkerType":"Chapter","ChapterIndex":77},{"StartPositionTicks":53835860000,"Name":"Chapter 79","MarkerType":"Chapter","ChapterIndex":78},{"StartPositionTicks":54371390000,"Name":"Chapter 80","MarkerType":"Chapter","ChapterIndex":79},{"StartPositionTicks":55125890000,"Name":"Chapter 81","MarkerType":"Chapter","ChapterIndex":80},{"StartPositionTicks":57107040000,"Name":"Chapter 82","MarkerType":"Chapter","ChapterIndex":81},{"StartPositionTicks":57457390000,"Name":"Chapter 83","MarkerType":"Chapter","ChapterIndex":82},{"StartPositionTicks":58119720000,"Name":"Chapter 84","MarkerType":"Chapter","ChapterIndex":83},{"StartPositionTicks":58988920000,"Name":"Chapter 85","MarkerType":"Chapter","ChapterIndex":84},{"StartPositionTicks":59258770000,"Name":"Chapter 86","MarkerType":"Chapter","ChapterIndex":85},{"StartPositionTicks":62192120000,"Name":"Chapter 87","MarkerType":"Chapter","ChapterIndex":86}]}]