[{"MediaSourceInfo":{"Protocol":"File","Type":"Default","Container":"mkv","Size":6072359859,"Name":"春江水暖 (2019) - 1080p.H.265","IsRemote":true,"HasMixedProtocols":false,"RunTimeTicks":90252800000,"SupportsTranscoding":true,"SupportsDirectStream":true,"SupportsDirectPlay":true,"IsInfiniteStream":false,"RequiresOpening":false,"RequiresClosing":false,"RequiresLooping":false,"SupportsProbing":false,"MediaStreams":[{"Codec":"ac3","TimeBase":"1/1000","DisplayTitle":"AC3 5.1 (默认)","IsInterlaced":false,"ChannelLayout":"5.1","BitRate":640000,"Channels":6,"SampleRate":48000,"IsDefault":true,"IsForced":false,"IsHearingImpaired":false,"Type":"Audio","Index":0,"IsExternal":false,"IsTextSubtitleStream":false,"SupportsExternalStream":false,"Protocol":"File","ExtendedVideoType":"None","ExtendedVideoSubType":"None","ExtendedVideoSubTypeDescription":"None","AttachmentSize":0},{"Codec":"PGSSUB","Language":"chi","TimeBase":"1/1000","Title":"chs","DisplayTitle":"Chinese Simplified (默认 PGSSUB)","DisplayLanguage":"Chinese Simplified","IsInterlaced":false,"IsDefault":true,"IsForced":false,"IsHearingImpaired":false,"Type":"Subtitle","Index":1,"IsExternal":false,"IsTextSubtitleStream":false,"SupportsExternalStream":false,"Protocol":"File","ExtendedVideoType":"None","ExtendedVideoSubType":"None","ExtendedVideoSubTypeDescription":"None","AttachmentSize":0,"SubtitleLocationType":"InternalStream"},{"Codec":"PGSSUB","Language":"chi","TimeBase":"1/1000","Title":"cht","DisplayTitle":"Chinese Simplified (PGSSUB)","DisplayLanguage":"Chinese Simplified","IsInterlaced":false,"IsDefault":false,"IsForced":false,"IsHearingImpaired":false,"Type":"Subtitle","Index":2,"IsExternal":false,"IsTextSubtitleStream":false,"SupportsExternalStream":false,"Protocol":"File","ExtendedVideoType":"None","ExtendedVideoSubType":"None","ExtendedVideoSubTypeDescription":"None","AttachmentSize":0,"SubtitleLocationType":"InternalStream"},{"Codec":"hevc","ColorTransfer":"bt709","ColorPrimaries":"bt709","ColorSpace":"bt709","TimeBase":"1/1000","VideoRange":"SDR","DisplayTitle":"1080p HEVC","IsInterlaced":false,"BitRate":5382534,"BitDepth":10,"RefFrames":1,"IsDefault":true,"IsForced":false,"IsHearingImpaired":false,"Height":1080,"Width":1920,"AverageFrameRate":23.976025,"RealFrameRate":23.976025,"Profile":"Main 10","Type":"Video","AspectRatio":"16:9","Index":3,"IsExternal":false,"IsTextSubtitleStream":false,"SupportsExternalStream":false,"Protocol":"File","PixelFormat":"yuv420p10le","Level":153,"IsAnamorphic":false,"ExtendedVideoType":"None","ExtendedVideoSubType":"None","ExtendedVideoSubTypeDescription":"None","AttachmentSize":0},{"Codec":"srt","Language":"zh-CN","DisplayTitle":"Chinese Simplified (SRT)","DisplayLanguage":"Chinese Simplified","IsInterlaced":false,"IsDefault":false,"IsForced":false,"IsHearingImpaired":false,"Type":"Subtitle","Index":4,"IsExternal":true,"IsTextSubtitleStream":true,"SupportsExternalStream":true,"Path":"春江水暖 (2019) - 1080p.H.265.3.zh-CN.srt","Protocol":"File","ExtendedVideoType":"None","ExtendedVideoSubType":"None","ExtendedVideoSubTypeDescription":"None","AttachmentSize":0},{"Codec":"srt","Language":"zh-CN","DisplayTitle":"Chinese Simplified (SRT)","DisplayLanguage":"Chinese Simplified","IsInterlaced":false,"IsDefault":false,"IsForced":false,"IsHearingImpaired":false,"Type":"Subtitle","Index":5,"IsExternal":true,"IsTextSubtitleStream":true,"SupportsExternalStream":true,"Path":"春江水暖 (2019) - 1080p.H.265.8.zh-CN.srt","Protocol":"File","ExtendedVideoType":"None","ExtendedVideoSubType":"None","ExtendedVideoSubTypeDescription":"None","AttachmentSize":0},{"Codec":"srt","Language":"zh-CN","DisplayTitle":"Chinese Simplified (SRT)","DisplayLanguage":"Chinese Simplified","IsInterlaced":false,"IsDefault":false,"IsForced":false,"IsHearingImpaired":false,"Type":"Subtitle","Index":6,"IsExternal":true,"IsTextSubtitleStream":true,"SupportsExternalStream":true,"Path":"春江水暖 (2019) - 1080p.H.265.10.zh-CN.srt","Protocol":"File","ExtendedVideoType":"None","ExtendedVideoSubType":"None","ExtendedVideoSubTypeDescription":"None","AttachmentSize":0},{"Codec":"srt","Language":"zh-CN","DisplayTitle":"Chinese Simplified (SRT)","DisplayLanguage":"Chinese Simplified","IsInterlaced":false,"IsDefault":false,"IsForced":false,"IsHearingImpaired":false,"Type":"Subtitle","Index":7,"IsExternal":true,"IsTextSubtitleStream":true,"SupportsExternalStream":true,"Path":"春江水暖 (2019) - 1080p.H.265.5.zh-CN.srt","Protocol":"File","ExtendedVideoType":"None","ExtendedVideoSubType":"None","ExtendedVideoSubTypeDescription":"None","AttachmentSize":0},{"Codec":"srt","Language":"zh-CN","DisplayTitle":"Chinese Simplified (SRT)","DisplayLanguage":"Chinese Simplified","IsInterlaced":false,"IsDefault":false,"IsForced":false,"IsHearingImpaired":false,"Type":"Subtitle","Index":8,"IsExternal":true,"IsTextSubtitleStream":true,"SupportsExternalStream":true,"Path":"春江水暖 (2019) - 1080p.H.265.7.zh-CN.srt","Protocol":"File","ExtendedVideoType":"None","ExtendedVideoSubType":"None","ExtendedVideoSubTypeDescription":"None","AttachmentSize":0},{"Codec":"srt","Language":"zh-CN","DisplayTitle":"Chinese Simplified (SRT)","DisplayLanguage":"Chinese Simplified","IsInterlaced":false,"IsDefault":false,"IsForced":false,"IsHearingImpaired":false,"Type":"Subtitle","Index":9,"IsExternal":true,"IsTextSubtitleStream":true,"SupportsExternalStream":true,"Path":"春江水暖 (2019) - 1080p.H.265.9.zh-CN.srt","Protocol":"File","ExtendedVideoType":"None","ExtendedVideoSubType":"None","ExtendedVideoSubTypeDescription":"None","AttachmentSize":0},{"Codec":"srt","Language":"zh-CN","DisplayTitle":"Chinese Simplified (SRT)","DisplayLanguage":"Chinese Simplified","IsInterlaced":false,"IsDefault":false,"IsForced":false,"IsHearingImpaired":false,"Type":"Subtitle","Index":10,"IsExternal":true,"IsTextSubtitleStream":true,"SupportsExternalStream":true,"Path":"春江水暖 (2019) - 1080p.H.265.1.zh-CN.srt","Protocol":"File","ExtendedVideoType":"None","ExtendedVideoSubType":"None","ExtendedVideoSubTypeDescription":"None","AttachmentSize":0},{"Codec":"srt","Language":"zh-CN","DisplayTitle":"Chinese Simplified (SRT)","DisplayLanguage":"Chinese Simplified","IsInterlaced":false,"IsDefault":false,"IsForced":false,"IsHearingImpaired":false,"Type":"Subtitle","Index":11,"IsExternal":true,"IsTextSubtitleStream":true,"SupportsExternalStream":true,"Path":"春江水暖 (2019) - 1080p.H.265.zh-CN.srt","Protocol":"File","ExtendedVideoType":"None","ExtendedVideoSubType":"None","ExtendedVideoSubTypeDescription":"None","AttachmentSize":0},{"Codec":"srt","Language":"zh-CN","DisplayTitle":"Chinese Simplified (SRT)","DisplayLanguage":"Chinese Simplified","IsInterlaced":false,"IsDefault":false,"IsForced":false,"IsHearingImpaired":false,"Type":"Subtitle","Index":12,"IsExternal":true,"IsTextSubtitleStream":true,"SupportsExternalStream":true,"Path":"春江水暖 (2019) - 1080p.H.265.6.zh-CN.srt","Protocol":"File","ExtendedVideoType":"None","ExtendedVideoSubType":"None","ExtendedVideoSubTypeDescription":"None","AttachmentSize":0},{"Codec":"srt","Language":"zh-CN","DisplayTitle":"Chinese Simplified (SRT)","DisplayLanguage":"Chinese Simplified","IsInterlaced":false,"IsDefault":false,"IsForced":false,"IsHearingImpaired":false,"Type":"Subtitle","Index":13,"IsExternal":true,"IsTextSubtitleStream":true,"SupportsExternalStream":true,"Path":"春江水暖 (2019) - 1080p.H.265.4.zh-CN.srt","Protocol":"File","ExtendedVideoType":"None","ExtendedVideoSubType":"None","ExtendedVideoSubTypeDescription":"None","AttachmentSize":0},{"Codec":"srt","Language":"zh-CN","DisplayTitle":"Chinese Simplified (SRT)","DisplayLanguage":"Chinese Simplified","IsInterlaced":false,"IsDefault":false,"IsForced":false,"IsHearingImpaired":false,"Type":"Subtitle","Index":14,"IsExternal":true,"IsTextSubtitleStream":true,"SupportsExternalStream":true,"Path":"春江水暖 (2019) - 1080p.H.265.2.zh-CN.srt","Protocol":"File","ExtendedVideoType":"None","ExtendedVideoSubType":"None","ExtendedVideoSubTypeDescription":"None","AttachmentSize":0}],"Formats":[],"Bitrate":5382534,"RequiredHttpHeaders":{},"AddApiKeyToDirectStreamUrl":false,"ReadAtNativeFramerate":false},"Chapters":[{"StartPositionTicks":0,"Name":"第 01 章","MarkerType":"Chapter","ChapterIndex":0},{"StartPositionTicks":5416240000,"Name":"第 02 章","MarkerType":"Chapter","ChapterIndex":1},{"StartPositionTicks":11774260000,"Name":"第 03 章","MarkerType":"Chapter","ChapterIndex":2},{"StartPositionTicks":18582310000,"Name":"第 04 章","MarkerType":"Chapter","ChapterIndex":3},{"StartPositionTicks":25768240000,"Name":"第 05 章","MarkerType":"Chapter","ChapterIndex":4},{"StartPositionTicks":31673730000,"Name":"第 06 章","MarkerType":"Chapter","ChapterIndex":5},{"StartPositionTicks":36245790000,"Name":"第 07 章","MarkerType":"Chapter","ChapterIndex":6},{"StartPositionTicks":42721430000,"Name":"第 08 章","MarkerType":"Chapter","ChapterIndex":7},{"StartPositionTicks":48386250000,"Name":"第 09 章","MarkerType":"Chapter","ChapterIndex":8},{"StartPositionTicks":55452060000,"Name":"第 10 章","MarkerType":"Chapter","ChapterIndex":9},{"StartPositionTicks":61286220000,"Name":"第 11 章","MarkerType":"Chapter","ChapterIndex":10},{"StartPositionTicks":67015280000,"Name":"第 12 章","MarkerType":"Chapter","ChapterIndex":11},{"StartPositionTicks":71740840000,"Name":"第 13 章","MarkerType":"Chapter","ChapterIndex":12},{"StartPositionTicks":76976900000,"Name":"第 14 章","MarkerType":"Chapter","ChapterIndex":13},{"StartPositionTicks":81827580000,"Name":"第 15 章","MarkerType":"Chapter","ChapterIndex":14},{"StartPositionTicks":86883880000,"Name":"第 16 章","MarkerType":"Chapter","ChapterIndex":15}]}]